Metadata-Version: 2.1
Name: sdklib
Version: 1.12.0
Summary: SDK helper library
Home-page: https://github.com/ivanprjcts/sdklib
Author: Ivan Martin
Author-email: ivanprjcts@gmail.com
License: BSD
Keywords: sdk,api,REST,client,http,requests
Platform: UNKNOWN
Classifier: Intended Audience :: Developers
Classifier: License :: OSI Approved :: BSD License
Classifier: Operating System :: OS Independent
Classifier: Programming Language :: Python
Classifier: Programming Language :: Python :: 2.7
Classifier: Programming Language :: Python :: 3.3
Classifier: Programming Language :: Python :: 3.4
Classifier: Programming Language :: Python :: 3.5
License-File: LICENSE
Requires-Dist: urllib3 (>=1.24.1)
Requires-Dist: html5lib (==1.1)
